GreatIdeasInTheoreticalComputerScienceLectureNotesMit6045/README.md
GreatIdeasInTheoreticalComputerScienceLectureNotesMit6045/__init__.py
GreatIdeasInTheoreticalComputerScienceLectureNotesMit6045/__main__.py
GreatIdeasInTheoreticalComputerScienceLectureNotesMit6045/file.pdf
GreatIdeasInTheoreticalComputerScienceLectureNotesMit6045/index.html
great_ideas_in_theoretical_computer_science_lecture_notes_mit_6_045-2024.3.2.0.dist-info/METADATA
great_ideas_in_theoretical_computer_science_lecture_notes_mit_6_045-2024.3.2.0.dist-info/WHEEL
great_ideas_in_theoretical_computer_science_lecture_notes_mit_6_045-2024.3.2.0.dist-info/entry_points.txt
great_ideas_in_theoretical_computer_science_lecture_notes_mit_6_045-2024.3.2.0.dist-info/top_level.txt
great_ideas_in_theoretical_computer_science_lecture_notes_mit_6_045-2024.3.2.0.dist-info/RECORD
